MANIFEST.in
setup.py
bin/puke
bin/puke.css.compress
bin/puke.js.compress
puke/Cache.py
puke/Cache.pyc
puke/Compress.py
puke/Compress.pyc
puke/Console.py
puke/Console.pyc
puke/Env.py
puke/Env.pyc
puke/Error.py
puke/Error.pyc
puke/FileList.py
puke/FileList.pyc
puke/FileSystem.py
puke/FileSystem.pyc
puke/Require.py
puke/Require.pyc
puke/SSH.py
puke/SSH.pyc
puke/Sed.py
puke/Sed.pyc
puke/Std.py
puke/Std.pyc
puke/System.py
puke/System.pyc
puke/Task.py
puke/Task.pyc
puke/Tools.py
puke/Tools.pyc
puke/ToolsExec.py
puke/ToolsExec.pyc
puke/Utils.py
puke/Utils.pyc
puke/VirtualEnv.py
puke/VirtualEnv.pyc
puke/Yak.py
puke/Yak.pyc
puke/__init__.py
puke/__init__.pyc
puke.egg-info/PKG-INFO
puke.egg-info/SOURCES.txt
puke.egg-info/dependency_links.txt
puke.egg-info/requires.txt
puke.egg-info/top_level.txt
puke/compat/__init__.py
puke/compat/__init__.pyc
puke/compat/grp.py
puke/compat/pwd.py
puke/compat/pwd.pyc
puke/datas/decoration/puke.txt
puke/datas/jsdoc-toolkit/README.txt
puke/datas/jsdoc-toolkit/changes.txt
puke/datas/jsdoc-toolkit/jsdebug.jar
puke/datas/jsdoc-toolkit/jsrun.jar
puke/datas/jsdoc-toolkit/jsrun.sh
puke/datas/jsdoc-toolkit/app/frame.js
puke/datas/jsdoc-toolkit/app/main.js
puke/datas/jsdoc-toolkit/app/run.js
puke/datas/jsdoc-toolkit/app/test.js
puke/datas/jsdoc-toolkit/app/frame/Chain.js
puke/datas/jsdoc-toolkit/app/frame/Dumper.js
puke/datas/jsdoc-toolkit/app/frame/Hash.js
puke/datas/jsdoc-toolkit/app/frame/Link.js
puke/datas/jsdoc-toolkit/app/frame/Namespace.js
puke/datas/jsdoc-toolkit/app/frame/Opt.js
puke/datas/jsdoc-toolkit/app/frame/Reflection.js
puke/datas/jsdoc-toolkit/app/frame/String.js
puke/datas/jsdoc-toolkit/app/frame/Testrun.js
puke/datas/jsdoc-toolkit/app/handlers/FOODOC.js
puke/datas/jsdoc-toolkit/app/handlers/XMLDOC.js
puke/datas/jsdoc-toolkit/app/handlers/XMLDOC/DomReader.js
puke/datas/jsdoc-toolkit/app/handlers/XMLDOC/XMLDoc.js
puke/datas/jsdoc-toolkit/app/handlers/XMLDOC/XMLParse.js
puke/datas/jsdoc-toolkit/app/lib/JSDOC.js
puke/datas/jsdoc-toolkit/app/lib/JSDOC/DocComment.js
puke/datas/jsdoc-toolkit/app/lib/JSDOC/DocTag.js
puke/datas/jsdoc-toolkit/app/lib/JSDOC/JsDoc.js
