Metadata-Version: 1.0
Name: puke
Version: 1.5.22
Summary: Puke is a straightforward build system
Home-page: http://github.com/webitup/puke
Author: Emmanuel Tabard
Author-email: manu@webitup.fr
License: http://www.gnu.org/copyleft/gpl.html
Keywords: build system python
Platform: UNKNOWN
